Metadata-Version: 2.1
Name: odoo-addon-partner_priority
Version: 18.0.1.0.0.5
Requires-Python: >=3.10
Requires-Dist: odoo==18.0.*
Summary: Adds priority to partners.
Home-page: https://github.com/OCA/partner-contact
License: AGPL-3
Author: Patrick Wilson, Odoo Community Association (OCA)
Author-email: support@odoo-community.org
Classifier: Programming Language :: Python
Classifier: Framework :: Odoo
Classifier: Framework :: Odoo :: 18.0
Classifier: License :: OSI Approved :: GNU Affero General Public License v3
Classifier: Development Status :: 4 - Beta
